MANIFEST.in
README.txt
setup.cfg
setup.py
anthill/__init__.py
anthill.querytool.egg-info/PKG-INFO
anthill.querytool.egg-info/SOURCES.txt
anthill.querytool.egg-info/dependency_links.txt
anthill.querytool.egg-info/entry_points.txt
anthill.querytool.egg-info/namespace_packages.txt
anthill.querytool.egg-info/not-zip-safe
anthill.querytool.egg-info/requires.txt
anthill.querytool.egg-info/top_level.txt
anthill/querytool/Query.py
anthill/querytool/QueryTool.py
anthill/querytool/SearchOperators.py
anthill/querytool/__init__.py
anthill/querytool/config.py
anthill/querytool/configure.zcml
anthill/querytool/patches.py
anthill/querytool/profiles.zcml
anthill/querytool/setuphandlers.py
anthill/querytool/tests.py
anthill/querytool/tool.gif
anthill/querytool/exportimport/__init__.py
anthill/querytool/exportimport/configure.zcml
anthill/querytool/exportimport/exportimport.py
anthill/querytool/exportimport/querytool.sample.xml
anthill/querytool/exportimport/tests/__init__.py
anthill/querytool/exportimport/tests/test_exportimport.py
anthill/querytool/profiles/querytool/import_steps.xml
anthill/querytool/www/predefined_queries.zpt
anthill/querytool/www/submit_query.zpt
docs/HISTORY.txt