Metadata-Version: 1.0
Name: anthill.querytool
Version: 0.2
Summary: GUI for AdvancedQuery with some extensions - searching the easy way for Plone
Home-page: http://www.banality.de/
Author: Simon Pamies
Author-email: s.pamies@banality.de
License: GPL
Keywords: anthill plone query advancedquery search
Platform: UNKNOWN
Classifier: Programming Language :: Python
Classifier: Topic :: Software Development :: Libraries :: Python Modules
